kabocha/__init__.py
kabocha/admin.py
kabocha/authentication.py
kabocha/authorization.py
kabocha/models.py
kabocha/resources.py
kabocha/tests.py
kabocha/views.py
kabocha/errors/__init__.py
kabocha/errors/application.py
kabocha/errors/auth.py
kabocha/errors/base.py
kabocha/errors/notfound.py
kabocha/errors/traceback.py
kabocha/errors/validation.py
kabocha-1.0.1.dist-info/LICENSE
kabocha-1.0.1.dist-info/METADATA
kabocha-1.0.1.dist-info/WHEEL
kabocha-1.0.1.dist-info/top_level.txt
kabocha-1.0.1.dist-info/RECORD
